{"version":1,"resource":"vscode-remote://ssh-remote%2Bteam11/home/team11/pintos/src/userprog/exception.c","entries":[{"id":"eoZD.c","timestamp":1670598950417},{"id":"MPy8.c","timestamp":1670598967096},{"id":"7GZh.c","timestamp":1670598980308},{"id":"YqMp.c","timestamp":1670598991324},{"id":"mJKZ.c","timestamp":1670599046138},{"id":"006Q.c","timestamp":1670599065594},{"id":"12m0.c","timestamp":1670599098153},{"id":"Nlem.c","timestamp":1670653257240},{"id":"9MPm.c","timestamp":1670653340614},{"id":"VaCc.c","timestamp":1670653368649},{"id":"pEuu.c","timestamp":1670653401432},{"id":"Nr60.c","timestamp":1670653436315},{"id":"SLSM.c","timestamp":1670653515521},{"id":"mJT7.c","timestamp":1670653530244},{"id":"sx7h.c","timestamp":1670653540624},{"id":"90md.c","timestamp":1670661767472},{"id":"UPPd.c","timestamp":1670662346517},{"id":"6B8B.c","timestamp":1670713442873},{"id":"ORLH.c","timestamp":1670713484000},{"id":"4uAl.c","timestamp":1670713495496},{"id":"iI5q.c","timestamp":1670713581417},{"id":"Xliz.c","timestamp":1670713648628},{"id":"Fapy.c","timestamp":1670713877258},{"id":"Lmux.c","timestamp":1670713899909},{"id":"PyzM.c","timestamp":1670713933084},{"id":"7bbC.c","timestamp":1670714214889},{"id":"QuK1.c","timestamp":1670714948310},{"id":"M8XU.c","timestamp":1670714987425},{"id":"sWrD.c","timestamp":1670715028676},{"id":"HGsJ.c","timestamp":1670715397718},{"id":"wOsO.c","timestamp":1670717286083},{"id":"SoXE.c","timestamp":1670717317466},{"id":"j8jN.c","timestamp":1670717337357},{"id":"7Jcl.c","timestamp":1670717348645},{"id":"KhCM.c","source":"undoRedo.source","timestamp":1670717690408},{"id":"uCtt.c","timestamp":1670717701008},{"id":"yR5Q.c","timestamp":1670719096195},{"id":"BMjc.c","timestamp":1670719107675},{"id":"cLbr.c","timestamp":1670722177750},{"id":"IufJ.c","timestamp":1670723684989},{"id":"obZg.c","timestamp":1670723797926},{"id":"kbDI.c","timestamp":1670723882500},{"id":"EqgM.c","timestamp":1670723985217},{"id":"Zcuk.c","timestamp":1670724010509},{"id":"3gfl.c","timestamp":1670724036232},{"id":"P7Un.c","timestamp":1670724054164},{"id":"U1rI.c","timestamp":1670724879449},{"id":"o7z0.c","timestamp":1670725779225},{"id":"uQOL.c","timestamp":1670725794977},{"id":"TOXr.c","timestamp":1671011401907}]}